pytest_pyvenv/__init__.py
pytest_pyvenv-0.2.4.dist-info/METADATA
pytest_pyvenv-0.2.4.dist-info/WHEEL
pytest_pyvenv-0.2.4.dist-info/entry_points.txt
pytest_pyvenv-0.2.4.dist-info/top_level.txt
pytest_pyvenv-0.2.4.dist-info/RECORD
